{
  "Model": "NPC/Pets/Corgi/Models/Model.blockymodel",
  "Texture": "NPC/Pets/Corgi/Models/Model_default.png",
  "EyeHeight": 0.6,
  "HitBox": {
    "Max": {
      "X": 0.3,
      "Y": 0.8,
      "Z": 0.3
    },
    "Min": {
      "X": -0.3,
      "Y": 0,
      "Z": -0.3
    }
  },
  "DefaultAttachments": [
    {
      "Model": "NPC/Pets/Corgi/Attachments/RedScarf.blockymodel",
      "Texture": "NPC/Pets/Corgi/Attachments/RedScarf.png"
    }
  ],
  "AnimationSets": {
    "Idle": {
      "Animations": [
        {
          "Animation": "NPC/Pets/Corgi/Animations/Idle.blockyanim",
          "Speed": 1
        }
      ]
    },
    "Walk": {
      "Animations": [
        {
          "Animation": "NPC/Pets/Corgi/Animations/Walk.blockyanim",
          "Speed": 0.8
        }
      ]
    },
    "WalkBackward": {
      "Animations": [
        {
          "Animation": "NPC/Pets/Corgi/Animations/Walk_Backward.blockyanim"
        }
      ]
    },
    "Run": {
      "Animations": [
        {
          "Animation": "NPC/Pets/Corgi/Animations/Run.blockyanim",
          "Speed": 1
        }
      ]
    },
    "Jump": {
      "Animations": [
        {
          "Animation": "NPC/Pets/Corgi/Animations/Jump.blockyanim",
          "BlendingDuration": 0.1,
          "Looping": false,
          "Speed": 0.8
        }
      ]
    },
    "JumpWalk": {
      "Animations": [
        {
          "Animation": "NPC/Pets/Corgi/Animations/Jump_Far.blockyanim",
          "BlendingDuration": 0.1,
          "Looping": false,
          "Speed": 0.8
        }
      ]
    },
    "JumpRun": {
      "Animations": [
        {
          "Animation": "NPC/Pets/Corgi/Animations/Jump_Far.blockyanim",
          "BlendingDuration": 0.1,
          "Looping": false,
          "Speed": 0.8
        }
      ]
    },
    "Fall": {
      "Animations": [
        {
          "Animation": "NPC/Pets/Corgi/Animations/Fall.blockyanim",
          "BlendingDuration": 0.4
        }
      ]
    },
    "Alerted": {
      "Animations": [
        {
          "Animation": "NPC/Pets/Corgi/Animations/Alerted.blockyanim",
          "Looping": false
        }
      ]
    },
    "Fly": {
      "Animations": [
        {
          "Animation": "NPC/Pets/Corgi/Animations/Fall.blockyanim",
          "Speed": 1
        }
      ]
    },
    "Hurt": {
      "Animations": [
        {
          "Animation": "NPC/Pets/Corgi/Animations/Hurt.blockyanim",
          "BlendingDuration": 0.1,
          "Looping": false
        }
      ]
    },
    "Death": {
      "Animations": [
        {
          "Animation": "NPC/Pets/Corgi/Animations/Death.blockyanim",
          "Looping": false
        },
        {
          "Animation": "NPC/Pets/Corgi/Animations/Death2.blockyanim",
          "Looping": false
        }
      ]
    },
    "Sleep": {
      "Animations": [
        {
          "Animation": "NPC/Pets/Corgi/Animations/Sleep.blockyanim"
        }
      ]
    },
    "IdlePassive": {
      "Animations": [
        {
          "Animation": "NPC/Pets/Corgi/Animations/Idles/Run_Circle.blockyanim"
        }
      ],
      "NextAnimationDelay": {
        "Max": 30,
        "Min": 5
      }
    },
    "Alerted2": {
      "Animations": [
        {
          "Animation": "NPC/Pets/Corgi/Animations/Alerted2.blockyanim",
          "Looping": true
        }
      ]
    }
  }
}