{
  "TranslationProperties": {
    "Name": "server.items.Armor_Onyxium_Chest.name"
  },
  "Parent": "Armor_Iron_Chest",
  "Recipe": {
    "Input": [],
    "BenchRequirement": []
  },
  "Quality": "Epic",
  "ItemLevel": 65,
  "Icon": "Icons/ItemsGenerated/Armor_Onyxium_Chest.png",
  "IconProperties": {
    "Scale": 0.305,
    "Rotation": [
      22.5,
      45,
      22.5
    ],
    "Translation": [
      0,
      -18
    ]
  },
  "Model": "Items/Armors/Onyxium/Chest.blockymodel",
  "Texture": "Items/Armors/Onyxium/Chest_Texture.png",
  "Armor": {
    "ArmorSlot": "Chest",
    "BaseDamageResistance": 0,
    "CosmeticsToHide": [
      "Overtop"
    ],
    "DamageResistance": {
      "Physical": [
        {
          "Amount": 0.09,
          "CalculationType": "Multiplicative"
        }
      ],
      "Projectile": [
        {
          "Amount": 0.09,
          "CalculationType": "Multiplicative"
        }
      ]
    },
    "StatModifiers": {
      "Health": [
        {
          "Amount": 17,
          "CalculationType": "Additive"
        }
      ],
      "Mana": [
        {
          "Amount": 16,
          "CalculationType": "Additive"
        }
      ]
    }
  },
  "Tags": {
    "Type": [
      "Armor"
    ],
    "Family": [
      "Onyxium"
    ]
  },
  "MaxDurability": 120,
  "ItemSoundSetId": "ISS_Armor_Heavy"
}