{
  "TranslationProperties": {
    "Name": "server.items.Furniture_Crude_Trapdoor.name"
  },
  "PlayerAnimationsId": "Block",
  "Categories": [
    "Furniture.Doors"
  ],
  "Set": "Furniture_Crude",
  "Icon": "Icons/ItemsGenerated/Furniture_Crude_Trapdoor.png",
  "IconProperties": {
    "Rotation": [
      22.5,
      45,
      22.5
    ],
    "Scale": 0.65,
    "Translation": [
      1,
      -26
    ]
  },
  "Interactions": {
    "Primary": "Block_Primary",
    "Secondary": "Block_Secondary"
  },
  "Recipe": {
    "Input": [
      {
        "ResourceTypeId": "Wood_Lightwood_Softwood"
      }
    ],
    "BenchRequirement": [
      {
        "Id": "Builders",
        "Type": "StructuralCrafting",
        "Categories": [
          "Trapdoor"
        ]
      }
    ]
  },
  "BlockType": {
    "BlockParticleSetId": "Wood",
    "CustomModel": "Blocks/Decorative_Sets/Crude/Trapdoor.blockymodel",
    "CustomModelTexture": [
      {
        "Texture": "Blocks/Decorative_Sets/Crude/Trapdoor_Texture.png",
        "Weight": 1
      }
    ],
    "DrawType": "Model",
    "Flags": {},
    "Gathering": {
      "Breaking": {
        "GatherType": "Woods"
      }
    },
    "HitboxType": "Trapdoor",
    "Material": "Solid",
    "Opacity": "Transparent",
    "ParticleColor": "#63412c",
    "State": {
      "Definitions": {
        "CloseDoorOut": {
          "InteractionSoundEventId": "SFX_Door_Crude_Close",
          "CustomModelAnimation": "Blocks/Animations/Trapdoor/Trapdoor_Close.blockyanim"
        },
        "OpenDoorOut": {
          "HitboxType": "Trapdoor_Open",
          "InteractionSoundEventId": "SFX_Door_Crude_Open",
          "CustomModelAnimation": "Blocks/Animations/Trapdoor/Trapdoor_Open.blockyanim"
        }
      }
    },
    "VariantRotation": "NESW",
    "BlockSoundSetId": "Wood",
    "IsDoor": true,
    "Interactions": {
      "Use": "Door_Horizontal"
    }
  },
  "ResourceTypes": [
    {
      "Id": "Fuel"
    },
    {
      "Id": "Charcoal"
    }
  ],
  "Tags": {
    "Type": [
      "Furniture"
    ],
    "Family": [
      "Crude"
    ]
  },
  "ItemSoundSetId": "ISS_Blocks_Wood"
}
