{
  "TranslationProperties": {
    "Name": "server.items.Rock_Shale_Brick_Roof_Flat.name"
  },
  "Icon": "Icons/ItemsGenerated/Rock_Shale_Brick_Roof_Flat.png",
  "Set": "Rock_Shale_Brick",
  "BlockType": {
    "CustomModelTexture": [
      {
        "Texture": "Blocks/Structures/Roofs/Slope_Rock_Textures/Shale_Brick.png",
        "Weight": 1
      }
    ],
    "Gathering": {
      "Breaking": {
        "GatherType": "Rocks"
      }
    },
    "ParticleColor": "#3d4a52"
  },
  "Tags": {
    "Type": [
      "Rock"
    ],
    "Family": [
      "Shale"
    ]
  },
  "Parent": "Rock_Stone_Brick_Roof_Flat",
  "Recipe": {
    "Input": [
      {
        "Quantity": 1,
        "ResourceTypeId": "Rock_Shale_Brick"
      }
    ],
    "BenchRequirement": [
      {
        "Id": "Builders",
        "Type": "StructuralCrafting",
        "Categories": [
          "Roof"
        ]
      }
    ],
    "OutputQuantity": 1,
    "TimeSeconds": 0
  }
}
