{
  "Conditions": {
    "EnvironmentTagPattern": {
      "Op": "And",
      "Patterns": [
        {
          "Op": "Equals",
          "Tag": "Caves"
        },
        {
          "Op": "Equals",
          "Tag": "Zone3"
        },
        {
          "Op": "Not",
          "Pattern": {
            "Op": "Equals",
            "Tag": "Volcanic"
          }
        }
      ]
    },
    "Roof": true
  },
  "Sounds": [
    {
      "SoundEventId": "SFX_Z3_Emit_Cave_Ice_Crackle",
      "Radius": {
        "Min": 3,
        "Max": 5
      },
      "Frequency": {
        "Min": 1,
        "Max": 10
      }
    },
    {
      "SoundEventId": "SFX_Z3_Emit_Cave_Snow_Melt",
      "Radius": {
        "Min": 3,
        "Max": 10
      },
      "Frequency": {
        "Min": 5,
        "Max": 10
      }
    },
    {
      "SoundEventId": "SFX_Z3_Emit_Cave_Ice_Rumble",
      "Radius": {
        "Min": 3,
        "Max": 5
      }
    },
    {
      "SoundEventId": "SFX_Z3_Emit_Cave_Ice_Stress",
      "Frequency": {
        "Min": 1,
        "Max": 10
      },
      "Radius": {
        "Min": 3,
        "Max": 5
      }
    },
    {
      "SoundEventId": "SFX_Z3_Emit_Cave_Snow_Crackle",
      "Radius": {
        "Min": 3,
        "Max": 5
      },
      "Frequency": {
        "Min": 1,
        "Max": 10
      }
    }
  ]
}
