{
  "TranslationProperties": {
    "Name": "server.items.Ingredient_Hide_Scaled.name",
    "Description": "server.items.Ingredient_Hide_Scaled.description"
  },
  "Categories": [
    "Items.Ingredients"
  ],
  "Model": "Resources/Materials/Hide.blockymodel",
  "Texture": "Resources/Materials/Hide_Textures/Scaled.png",
  "Quality": "Common",
  "ItemLevel": 10,
  "PlayerAnimationsId": "Item",
  "IconProperties": {
    "Scale": 0.52,
    "Translation": [
      1.5,
      -5.7
    ],
    "Rotation": [
      22.5,
      45,
      22.5
    ]
  },
  "Scale": 1.5,
  "Icon": "Icons/ItemsGenerated/Ingredient_Hide_Scaled.png",
  "Tags": {
    "Type": [
      "Ingredient"
    ],
    "Family": [
      "Hide"
    ]
  },
  "ItemEntity": {
    "ParticleSystemId": null
  },
  "DropOnDeath": true
}
