{
  "Layers": [
    {
      "Files": [
        "Sounds/NPC/Beasts/Deer_Stag/Deer_Stag_Alerted_01.ogg",
        "Sounds/NPC/Beasts/Deer_Stag/Deer_Stag_Alerted_02.ogg",
        "Sounds/NPC/Beasts/Deer_Stag/Deer_Stag_Alerted_03.ogg"
      ],
      "RandomSettings": {
        "MinPitch": -3.8631371386483475,
        "MaxPitch": 1.6500422849992202,
        "MinVolume": -13.979400086720375
      },
      "Probability": 100,
      "StartDelay": 0.3
    }
  ],
  "MaxInstance": 2,
  "Volume": -1.0,
  "PreventSoundInterruption": true,
  "AudioCategory": "AudioCat_NPC_Deer",
  "Parent": "SFX_Attn_Moderate"
}