{
  "Parent": "Moose_Cow",
  "Model": "NPC/Wildlife/Moose/Models/Model.blockymodel",
  "Texture": "NPC/Wildlife/Moose/Models/Model_Bull.png",
  "HitBox": {
    "Max": {
      "X": 0.6,
      "Y": 2,
      "Z": 0.6
    },
    "Min": {
      "X": -0.6,
      "Y": 0,
      "Z": -0.6
    }
  },
  "MinScale": 1.05,
  "MaxScale": 1.2,
  "DefaultAttachments": [
    {
      "Model": "NPC/Wildlife/Moose/Models/Attachments/Antlers.blockymodel",
      "Texture": "NPC/Wildlife/Moose/Models/Attachments/Antlers_Bull.png"
    }
  ],
  "AnimationSets": {
    "Alerted": {
      "Animations": [
        {
          "Animation": "NPC/Wildlife/Deer/Animations/Default/Alerted.blockyanim",
          "Looping": false,
          "SoundEventId": "SFX_Moose_Bull_Alerted"
        }
      ]
    }
  }
}