{
  "TranslationProperties": {
    "Name": "server.items.Furniture_Human_Ruins_Chair.name"
  },
  "PlayerAnimationsId": "Block",
  "Categories": [
    "Furniture.Furniture"
  ],
  "Set": "Furniture_Human_Ruins",
  "IconProperties": {
    "Rotation": [
      22.5,
      45,
      22.5
    ],
    "Scale": 0.5,
    "Translation": [
      2.5,
      -18.6
    ]
  },
  "BlockType": {
    "BlockParticleSetId": "Wood",
    "CustomModel": "Blocks/Decorative_Sets/Human_Ruins/Chair.blockymodel",
    "CustomModelTexture": [
      {
        "Texture": "Blocks/Decorative_Sets/Human_Ruins/Chair_Texture.png",
        "Weight": 1
      }
    ],
    "DrawType": "Model",
    "Flags": {},
    "Gathering": {
      "Breaking": {
        "GatherType": "Woods"
      }
    },
    "Group": "Wood",
    "HitboxType": "Chair",
    "Material": "Solid",
    "Opacity": "Transparent",
    "ParticleColor": "#4e462c",
    "Support": {
      "Down": [
        {
          "FaceType": "Full"
        }
      ]
    },
    "Seats": [
      {
        "Offset": {
          "X": 0,
          "Y": 0.01,
          "Z": 0.15
        },
        "Yaw": 0
      }
    ],
    "Interactions": {
      "Use": "Block_Seat"
    },
    "VariantRotation": "NESW",
    "BlockSoundSetId": "Wood"
  },
  "Model": "Blocks/Decorative_Sets/Tavern/Table.blockymodel",
  "Texture": "Blocks/Decorative_Sets/Tavern/Chair_Texture.png",
  "ResourceTypes": [
    {
      "Id": "Fuel"
    },
    {
      "Id": "Charcoal"
    }
  ],
  "Icon": "Icons/ItemsGenerated/Furniture_Human_Ruins_Chair.png",
  "Tags": {
    "Type": [
      "Furniture"
    ],
    "Family": [
      "Human"
    ]
  },
  "ItemSoundSetId": "ISS_Blocks_Wood"
}