{
  "ConnectsToOtherMaterials": true,
  "ConnectsToOtherTemplates": true,
  "DontUpdateAfterInitialPlacement": true,
  "DefaultShape": "Default",
  "Shapes": {
    "Default": {
      "PatternsToMatchAnyOf": [
        {
          "Type": "Custom",
          "TransformRulesToOrientation": true,
          "YawToApplyAddReplacedBlockType": "OneEighty",
          "RulesToMatch": [
            {
              "Position": {
                "X": -3,
                "Y": 0,
                "Z": 0
              },
              "IncludeOrExclude": "Include",
              "Shapes": [
                "Default"
              ]
            },
            {
              "Position": {
                "X": 3,
                "Y": 0,
                "Z": 0
              },
              "IncludeOrExclude": "Exclude",
              "Shapes": [
                "Default|Yaw=180"
              ]
            }
          ]
        }
      ]
    }
  }
}
