{
  "TranslationProperties": {
    "Name": "server.items.Soil_Gravel_Sand.name"
  },
  "Parent": "Soil_Gravel",
  "Icon": "Icons/ItemsGenerated/Soil_Gravel_Sand.png",
  "Recipe": {
    "TimeSeconds": 0,
    "Input": [
      {
        "ResourceTypeId": "Rubble",
        "Quantity": 3
      }
    ],
    "BenchRequirement": [
      {
        "Type": "Crafting",
        "Id": "Farmingbench",
        "Categories": [
          "Decorative"
        ]
      }
    ],
    "OutputQuantity": 1
  },
  "BlockType": {
    "Textures": [
      {
        "All": "BlockTextures/Soil_Gravel_Sand.png",
        "Weight": 1
      }
    ],
    "Gathering": {
      "Breaking": {
        "GatherType": "Soils",
        "DropList": "Rubble_Sandstone"
      },
      "UseDefaultDropWhenPlaced": true
    },
    "ParticleColor": "#c69f4f",
    "TransitionTexture": "BlockTextures/Transition_Gravel_Sand.png"
  }
}